{
  "por": [
    {
      "question1": "kk",
      "question2": "uu",
      "opt1": "0",
      "opt2": "19",
      "opt3": "38",
      "opt4": "57",
      "opt5": "76",
      "id": 1
    },
    {
      "opt1": "6",
      "opt2": "26",
      "opt3": "53",
      "opt4": "72",
      "opt5": "91",
      "id": 2
    },
    {
      "opt1": "4",
      "opt2": "23",
      "opt3": "42",
      "opt4": "61",
      "opt5": "80",
      "id": 3
    },
    {
      "opt1": "-1",
      "opt2": "-1",
      "opt3": "40",
      "opt4": "60",
      "opt5": "81",
      "id": 4
    },
    {
      "opt1": "-1",
      "opt2": "-1",
      "opt3": "-1",
      "opt4": "59",
      "opt5": "-1",
      "id": 5
    },
    {
      "opt1": "-1",
      "opt2": "-1",
      "opt3": "-1",
      "opt4": "-1",
      "opt5": "-1",
      "id": 6
    },
    {
      "opt1": "5",
      "opt2": "32",
      "opt3": "49",
      "opt4": "72",
      "opt5": "85",
      "id": 7
    },
    {
      "opt1": "-1",
      "opt2": "-1",
      "opt3": "-1",
      "opt4": "-1",
      "opt5": "-1",
      "id": 8
    }
  ]
}